restible
