Metadata-Version: 1.1
Name: restible
Version: 0.12
Summary: Python library to help building RESTful APIs
Home-page: http://github.com/novopl/restible
Author: Mateusz 'novo' Klos
Author-email: novopl@gmail.com
License: Apache 2.0
Keywords: restible REST restapi rest server restless
Platform: UNKNOWN
Classifier: Development Status :: 4 - Beta
Classifier: Topic :: Utilities
Classifier: Intended Audience :: Developers
Classifier: Programming Language :: Python
Classifier: License :: OSI Approved :: MIT License
